[
    {
        "level": 1,
        "statCurves": {
            "growthCurveHp4Star": 1.0,
            "growthCurveAtk4Star": 1.0,
            "growthCurveHp5Star": 1.0,
            "growthCurveAtk5Star": 1.0
        }
    },
    {
        "level": 2,
        "statCurves": {
            "growthCurveHp4Star": 1.0829999446868896,
            "growthCurveAtk4Star": 1.0829999446868896,
            "growthCurveHp5Star": 1.0829999446868896,
            "growthCurveAtk5Star": 1.0829999446868896
        }
    },
    {
        "level": 3,
        "statCurves": {
            "growthCurveHp4Star": 1.1649999618530273,
            "growthCurveAtk4Star": 1.1649999618530273,
            "growthCurveHp5Star": 1.1660000085830688,
            "growthCurveAtk5Star": 1.1660000085830688
        }
    },
    {
        "level": 4,
        "statCurves": {
            "growthCurveHp4Star": 1.2480000257492065,
            "growthCurveAtk4Star": 1.2480000257492065,
            "growthCurveHp5Star": 1.25,
            "growthCurveAtk5Star": 1.25
        }
    },
    {
        "level": 5,
        "statCurves": {
            "growthCurveHp4Star": 1.3300000429153442,
            "growthCurveAtk4Star": 1.3300000429153442,
            "growthCurveHp5Star": 1.3329999446868896,
            "growthCurveAtk5Star": 1.3329999446868896
        }
    },
    {
        "level": 6,
        "statCurves": {
            "growthCurveHp4Star": 1.4129999876022339,
            "growthCurveAtk4Star": 1.4129999876022339,
            "growthCurveHp5Star": 1.4170000553131104,
            "growthCurveAtk5Star": 1.4170000553131104
        }
    },
    {
        "level": 7,
        "statCurves": {
            "growthCurveHp4Star": 1.4950000047683716,
            "growthCurveAtk4Star": 1.4950000047683716,
            "growthCurveHp5Star": 1.5,
            "growthCurveAtk5Star": 1.5
        }
    },
    {
        "level": 8,
        "statCurves": {
            "growthCurveHp4Star": 1.5779999494552612,
            "growthCurveAtk4Star": 1.5779999494552612,
            "growthCurveHp5Star": 1.5839999914169312,
            "growthCurveAtk5Star": 1.5839999914169312
        }
    },
    {
        "level": 9,
        "statCurves": {
            "growthCurveHp4Star": 1.6610000133514404,
            "growthCurveAtk4Star": 1.6610000133514404,
            "growthCurveHp5Star": 1.6679999828338623,
            "growthCurveAtk5Star": 1.6679999828338623
        }
    },
    {
        "level": 10,
        "statCurves": {
            "growthCurveHp4Star": 1.7430000305175781,
            "growthCurveAtk4Star": 1.7430000305175781,
            "growthCurveHp5Star": 1.7510000467300415,
            "growthCurveAtk5Star": 1.7510000467300415
        }
    },
    {
        "level": 11,
        "statCurves": {
            "growthCurveHp4Star": 1.8259999752044678,
            "growthCurveAtk4Star": 1.8259999752044678,
            "growthCurveHp5Star": 1.8350000381469727,
            "growthCurveAtk5Star": 1.8350000381469727
        }
    },
    {
        "level": 12,
        "statCurves": {
            "growthCurveHp4Star": 1.9079999923706055,
            "growthCurveAtk4Star": 1.9079999923706055,
            "growthCurveHp5Star": 1.9190000295639038,
            "growthCurveAtk5Star": 1.9190000295639038
        }
    },
    {
        "level": 13,
        "statCurves": {
            "growthCurveHp4Star": 1.9910000562667847,
            "growthCurveAtk4Star": 1.9910000562667847,
            "growthCurveHp5Star": 2.003000020980835,
            "growthCurveAtk5Star": 2.003000020980835
        }
    },
    {
        "level": 14,
        "statCurves": {
            "growthCurveHp4Star": 2.072999954223633,
            "growthCurveAtk4Star": 2.072999954223633,
            "growthCurveHp5Star": 2.0880000591278076,
            "growthCurveAtk5Star": 2.0880000591278076
        }
    },
    {
        "level": 15,
        "statCurves": {
            "growthCurveHp4Star": 2.1559998989105225,
            "growthCurveAtk4Star": 2.1559998989105225,
            "growthCurveHp5Star": 2.171999931335449,
            "growthCurveAtk5Star": 2.171999931335449
        }
    },
    {
        "level": 16,
        "statCurves": {
            "growthCurveHp4Star": 2.239000082015991,
            "growthCurveAtk4Star": 2.239000082015991,
            "growthCurveHp5Star": 2.25600004196167,
            "growthCurveAtk5Star": 2.25600004196167
        }
    },
    {
        "level": 17,
        "statCurves": {
            "growthCurveHp4Star": 2.321000099182129,
            "growthCurveAtk4Star": 2.321000099182129,
            "growthCurveHp5Star": 2.3410000801086426,
            "growthCurveAtk5Star": 2.3410000801086426
        }
    },
    {
        "level": 18,
        "statCurves": {
            "growthCurveHp4Star": 2.4040000438690186,
            "growthCurveAtk4Star": 2.4040000438690186,
            "growthCurveHp5Star": 2.424999952316284,
            "growthCurveAtk5Star": 2.424999952316284
        }
    },
    {
        "level": 19,
        "statCurves": {
            "growthCurveHp4Star": 2.4860000610351562,
            "growthCurveAtk4Star": 2.4860000610351562,
            "growthCurveHp5Star": 2.509999990463257,
            "growthCurveAtk5Star": 2.509999990463257
        }
    },
    {
        "level": 20,
        "statCurves": {
            "growthCurveHp4Star": 2.569000005722046,
            "growthCurveAtk4Star": 2.569000005722046,
            "growthCurveHp5Star": 2.5940001010894775,
            "growthCurveAtk5Star": 2.5940001010894775
        }
    },
    {
        "level": 21,
        "statCurves": {
            "growthCurveHp4Star": 2.6510000228881836,
            "growthCurveAtk4Star": 2.6510000228881836,
            "growthCurveHp5Star": 2.678999900817871,
            "growthCurveAtk5Star": 2.678999900817871
        }
    },
    {
        "level": 22,
        "statCurves": {
            "growthCurveHp4Star": 2.7339999675750732,
            "growthCurveAtk4Star": 2.7339999675750732,
            "growthCurveHp5Star": 2.7639999389648438,
            "growthCurveAtk5Star": 2.7639999389648438
        }
    },
    {
        "level": 23,
        "statCurves": {
            "growthCurveHp4Star": 2.816999912261963,
            "growthCurveAtk4Star": 2.816999912261963,
            "growthCurveHp5Star": 2.8489999771118164,
            "growthCurveAtk5Star": 2.8489999771118164
        }
    },
    {
        "level": 24,
        "statCurves": {
            "growthCurveHp4Star": 2.8989999294281006,
            "growthCurveAtk4Star": 2.8989999294281006,
            "growthCurveHp5Star": 2.934000015258789,
            "growthCurveAtk5Star": 2.934000015258789
        }
    },
    {
        "level": 25,
        "statCurves": {
            "growthCurveHp4Star": 2.9820001125335693,
            "growthCurveAtk4Star": 2.9820001125335693,
            "growthCurveHp5Star": 3.0190000534057617,
            "growthCurveAtk5Star": 3.0190000534057617
        }
    },
    {
        "level": 26,
        "statCurves": {
            "growthCurveHp4Star": 3.063999891281128,
            "growthCurveAtk4Star": 3.063999891281128,
            "growthCurveHp5Star": 3.1050000190734863,
            "growthCurveAtk5Star": 3.1050000190734863
        }
    },
    {
        "level": 27,
        "statCurves": {
            "growthCurveHp4Star": 3.1470000743865967,
            "growthCurveAtk4Star": 3.1470000743865967,
            "growthCurveHp5Star": 3.190000057220459,
            "growthCurveAtk5Star": 3.190000057220459
        }
    },
    {
        "level": 28,
        "statCurves": {
            "growthCurveHp4Star": 3.2290000915527344,
            "growthCurveAtk4Star": 3.2290000915527344,
            "growthCurveHp5Star": 3.2750000953674316,
            "growthCurveAtk5Star": 3.2750000953674316
        }
    },
    {
        "level": 29,
        "statCurves": {
            "growthCurveHp4Star": 3.312000036239624,
            "growthCurveAtk4Star": 3.312000036239624,
            "growthCurveHp5Star": 3.3610000610351562,
            "growthCurveAtk5Star": 3.3610000610351562
        }
    },
    {
        "level": 30,
        "statCurves": {
            "growthCurveHp4Star": 3.3940000534057617,
            "growthCurveAtk4Star": 3.3940000534057617,
            "growthCurveHp5Star": 3.446000099182129,
            "growthCurveAtk5Star": 3.446000099182129
        }
    },
    {
        "level": 31,
        "statCurves": {
            "growthCurveHp4Star": 3.4769999980926514,
            "growthCurveAtk4Star": 3.4769999980926514,
            "growthCurveHp5Star": 3.5320000648498535,
            "growthCurveAtk5Star": 3.5320000648498535
        }
    },
    {
        "level": 32,
        "statCurves": {
            "growthCurveHp4Star": 3.559999942779541,
            "growthCurveAtk4Star": 3.559999942779541,
            "growthCurveHp5Star": 3.618000030517578,
            "growthCurveAtk5Star": 3.618000030517578
        }
    },
    {
        "level": 33,
        "statCurves": {
            "growthCurveHp4Star": 3.6419999599456787,
            "growthCurveAtk4Star": 3.6419999599456787,
            "growthCurveHp5Star": 3.7039999961853027,
            "growthCurveAtk5Star": 3.7039999961853027
        }
    },
    {
        "level": 34,
        "statCurves": {
            "growthCurveHp4Star": 3.7249999046325684,
            "growthCurveAtk4Star": 3.7249999046325684,
            "growthCurveHp5Star": 3.7890000343322754,
            "growthCurveAtk5Star": 3.7890000343322754
        }
    },
    {
        "level": 35,
        "statCurves": {
            "growthCurveHp4Star": 3.806999921798706,
            "growthCurveAtk4Star": 3.806999921798706,
            "growthCurveHp5Star": 3.875,
            "growthCurveAtk5Star": 3.875
        }
    },
    {
        "level": 36,
        "statCurves": {
            "growthCurveHp4Star": 3.890000104904175,
            "growthCurveAtk4Star": 3.890000104904175,
            "growthCurveHp5Star": 3.9619998931884766,
            "growthCurveAtk5Star": 3.9619998931884766
        }
    },
    {
        "level": 37,
        "statCurves": {
            "growthCurveHp4Star": 3.9719998836517334,
            "growthCurveAtk4Star": 3.9719998836517334,
            "growthCurveHp5Star": 4.047999858856201,
            "growthCurveAtk5Star": 4.047999858856201
        }
    },
    {
        "level": 38,
        "statCurves": {
            "growthCurveHp4Star": 4.054999828338623,
            "growthCurveAtk4Star": 4.054999828338623,
            "growthCurveHp5Star": 4.133999824523926,
            "growthCurveAtk5Star": 4.133999824523926
        }
    },
    {
        "level": 39,
        "statCurves": {
            "growthCurveHp4Star": 4.138000011444092,
            "growthCurveAtk4Star": 4.138000011444092,
            "growthCurveHp5Star": 4.21999979019165,
            "growthCurveAtk5Star": 4.21999979019165
        }
    },
    {
        "level": 40,
        "statCurves": {
            "growthCurveHp4Star": 4.21999979019165,
            "growthCurveAtk4Star": 4.21999979019165,
            "growthCurveHp5Star": 4.307000160217285,
            "growthCurveAtk5Star": 4.307000160217285
        }
    },
    {
        "level": 41,
        "statCurves": {
            "growthCurveHp4Star": 4.302999973297119,
            "growthCurveAtk4Star": 4.302999973297119,
            "growthCurveHp5Star": 4.39300012588501,
            "growthCurveAtk5Star": 4.39300012588501
        }
    },
    {
        "level": 42,
        "statCurves": {
            "growthCurveHp4Star": 4.385000228881836,
            "growthCurveAtk4Star": 4.385000228881836,
            "growthCurveHp5Star": 4.480000019073486,
            "growthCurveAtk5Star": 4.480000019073486
        }
    },
    {
        "level": 43,
        "statCurves": {
            "growthCurveHp4Star": 4.4679999351501465,
            "growthCurveAtk4Star": 4.4679999351501465,
            "growthCurveHp5Star": 4.566999912261963,
            "growthCurveAtk5Star": 4.566999912261963
        }
    },
    {
        "level": 44,
        "statCurves": {
            "growthCurveHp4Star": 4.550000190734863,
            "growthCurveAtk4Star": 4.550000190734863,
            "growthCurveHp5Star": 4.6529998779296875,
            "growthCurveAtk5Star": 4.6529998779296875
        }
    },
    {
        "level": 45,
        "statCurves": {
            "growthCurveHp4Star": 4.632999897003174,
            "growthCurveAtk4Star": 4.632999897003174,
            "growthCurveHp5Star": 4.739999771118164,
            "growthCurveAtk5Star": 4.739999771118164
        }
    },
    {
        "level": 46,
        "statCurves": {
            "growthCurveHp4Star": 4.716000080108643,
            "growthCurveAtk4Star": 4.716000080108643,
            "growthCurveHp5Star": 4.827000141143799,
            "growthCurveAtk5Star": 4.827000141143799
        }
    },
    {
        "level": 47,
        "statCurves": {
            "growthCurveHp4Star": 4.797999858856201,
            "growthCurveAtk4Star": 4.797999858856201,
            "growthCurveHp5Star": 4.914000034332275,
            "growthCurveAtk5Star": 4.914000034332275
        }
    },
    {
        "level": 48,
        "statCurves": {
            "growthCurveHp4Star": 4.88100004196167,
            "growthCurveAtk4Star": 4.88100004196167,
            "growthCurveHp5Star": 5.000999927520752,
            "growthCurveAtk5Star": 5.000999927520752
        }
    },
    {
        "level": 49,
        "statCurves": {
            "growthCurveHp4Star": 4.9629998207092285,
            "growthCurveAtk4Star": 4.9629998207092285,
            "growthCurveHp5Star": 5.089000225067139,
            "growthCurveAtk5Star": 5.089000225067139
        }
    },
    {
        "level": 50,
        "statCurves": {
            "growthCurveHp4Star": 5.046000003814697,
            "growthCurveAtk4Star": 5.046000003814697,
            "growthCurveHp5Star": 5.176000118255615,
            "growthCurveAtk5Star": 5.176000118255615
        }
    },
    {
        "level": 51,
        "statCurves": {
            "growthCurveHp4Star": 5.127999782562256,
            "growthCurveAtk4Star": 5.127999782562256,
            "growthCurveHp5Star": 5.263000011444092,
            "growthCurveAtk5Star": 5.263000011444092
        }
    },
    {
        "level": 52,
        "statCurves": {
            "growthCurveHp4Star": 5.210999965667725,
            "growthCurveAtk4Star": 5.210999965667725,
            "growthCurveHp5Star": 5.35099983215332,
            "growthCurveAtk5Star": 5.35099983215332
        }
    },
    {
        "level": 53,
        "statCurves": {
            "growthCurveHp4Star": 5.294000148773193,
            "growthCurveAtk4Star": 5.294000148773193,
            "growthCurveHp5Star": 5.438000202178955,
            "growthCurveAtk5Star": 5.438000202178955
        }
    },
    {
        "level": 54,
        "statCurves": {
            "growthCurveHp4Star": 5.375999927520752,
            "growthCurveAtk4Star": 5.375999927520752,
            "growthCurveHp5Star": 5.526000022888184,
            "growthCurveAtk5Star": 5.526000022888184
        }
    },
    {
        "level": 55,
        "statCurves": {
            "growthCurveHp4Star": 5.459000110626221,
            "growthCurveAtk4Star": 5.459000110626221,
            "growthCurveHp5Star": 5.613999843597412,
            "growthCurveAtk5Star": 5.613999843597412
        }
    },
    {
        "level": 56,
        "statCurves": {
            "growthCurveHp4Star": 5.540999889373779,
            "growthCurveAtk4Star": 5.540999889373779,
            "growthCurveHp5Star": 5.702000141143799,
            "growthCurveAtk5Star": 5.702000141143799
        }
    },
    {
        "level": 57,
        "statCurves": {
            "growthCurveHp4Star": 5.624000072479248,
            "growthCurveAtk4Star": 5.624000072479248,
            "growthCurveHp5Star": 5.789999961853027,
            "growthCurveAtk5Star": 5.789999961853027
        }
    },
    {
        "level": 58,
        "statCurves": {
            "growthCurveHp4Star": 5.705999851226807,
            "growthCurveAtk4Star": 5.705999851226807,
            "growthCurveHp5Star": 5.877999782562256,
            "growthCurveAtk5Star": 5.877999782562256
        }
    },
    {
        "level": 59,
        "statCurves": {
            "growthCurveHp4Star": 5.789000034332275,
            "growthCurveAtk4Star": 5.789000034332275,
            "growthCurveHp5Star": 5.966000080108643,
            "growthCurveAtk5Star": 5.966000080108643
        }
    },
    {
        "level": 60,
        "statCurves": {
            "growthCurveHp4Star": 5.872000217437744,
            "growthCurveAtk4Star": 5.872000217437744,
            "growthCurveHp5Star": 6.053999900817871,
            "growthCurveAtk5Star": 6.053999900817871
        }
    },
    {
        "level": 61,
        "statCurves": {
            "growthCurveHp4Star": 5.953999996185303,
            "growthCurveAtk4Star": 5.953999996185303,
            "growthCurveHp5Star": 6.142000198364258,
            "growthCurveAtk5Star": 6.142000198364258
        }
    },
    {
        "level": 62,
        "statCurves": {
            "growthCurveHp4Star": 6.0370001792907715,
            "growthCurveAtk4Star": 6.0370001792907715,
            "growthCurveHp5Star": 6.230000019073486,
            "growthCurveAtk5Star": 6.230000019073486
        }
    },
    {
        "level": 63,
        "statCurves": {
            "growthCurveHp4Star": 6.11899995803833,
            "growthCurveAtk4Star": 6.11899995803833,
            "growthCurveHp5Star": 6.318999767303467,
            "growthCurveAtk5Star": 6.318999767303467
        }
    },
    {
        "level": 64,
        "statCurves": {
            "growthCurveHp4Star": 6.202000141143799,
            "growthCurveAtk4Star": 6.202000141143799,
            "growthCurveHp5Star": 6.4070000648498535,
            "growthCurveAtk5Star": 6.4070000648498535
        }
    },
    {
        "level": 65,
        "statCurves": {
            "growthCurveHp4Star": 6.283999919891357,
            "growthCurveAtk4Star": 6.283999919891357,
            "growthCurveHp5Star": 6.495999813079834,
            "growthCurveAtk5Star": 6.495999813079834
        }
    },
    {
        "level": 66,
        "statCurves": {
            "growthCurveHp4Star": 6.367000102996826,
            "growthCurveAtk4Star": 6.367000102996826,
            "growthCurveHp5Star": 6.585000038146973,
            "growthCurveAtk5Star": 6.585000038146973
        }
    },
    {
        "level": 67,
        "statCurves": {
            "growthCurveHp4Star": 6.449999809265137,
            "growthCurveAtk4Star": 6.449999809265137,
            "growthCurveHp5Star": 6.672999858856201,
            "growthCurveAtk5Star": 6.672999858856201
        }
    },
    {
        "level": 68,
        "statCurves": {
            "growthCurveHp4Star": 6.5320000648498535,
            "growthCurveAtk4Star": 6.5320000648498535,
            "growthCurveHp5Star": 6.76200008392334,
            "growthCurveAtk5Star": 6.76200008392334
        }
    },
    {
        "level": 69,
        "statCurves": {
            "growthCurveHp4Star": 6.614999771118164,
            "growthCurveAtk4Star": 6.614999771118164,
            "growthCurveHp5Star": 6.85099983215332,
            "growthCurveAtk5Star": 6.85099983215332
        }
    },
    {
        "level": 70,
        "statCurves": {
            "growthCurveHp4Star": 6.697000026702881,
            "growthCurveAtk4Star": 6.697000026702881,
            "growthCurveHp5Star": 6.940000057220459,
            "growthCurveAtk5Star": 6.940000057220459
        }
    },
    {
        "level": 71,
        "statCurves": {
            "growthCurveHp4Star": 6.78000020980835,
            "growthCurveAtk4Star": 6.78000020980835,
            "growthCurveHp5Star": 7.0289998054504395,
            "growthCurveAtk5Star": 7.0289998054504395
        }
    },
    {
        "level": 72,
        "statCurves": {
            "growthCurveHp4Star": 6.861999988555908,
            "growthCurveAtk4Star": 6.861999988555908,
            "growthCurveHp5Star": 7.11899995803833,
            "growthCurveAtk5Star": 7.11899995803833
        }
    },
    {
        "level": 73,
        "statCurves": {
            "growthCurveHp4Star": 6.945000171661377,
            "growthCurveAtk4Star": 6.945000171661377,
            "growthCurveHp5Star": 7.208000183105469,
            "growthCurveAtk5Star": 7.208000183105469
        }
    },
    {
        "level": 74,
        "statCurves": {
            "growthCurveHp4Star": 7.0279998779296875,
            "growthCurveAtk4Star": 7.0279998779296875,
            "growthCurveHp5Star": 7.296999931335449,
            "growthCurveAtk5Star": 7.296999931335449
        }
    },
    {
        "level": 75,
        "statCurves": {
            "growthCurveHp4Star": 7.110000133514404,
            "growthCurveAtk4Star": 7.110000133514404,
            "growthCurveHp5Star": 7.38700008392334,
            "growthCurveAtk5Star": 7.38700008392334
        }
    },
    {
        "level": 76,
        "statCurves": {
            "growthCurveHp4Star": 7.192999839782715,
            "growthCurveAtk4Star": 7.192999839782715,
            "growthCurveHp5Star": 7.47599983215332,
            "growthCurveAtk5Star": 7.47599983215332
        }
    },
    {
        "level": 77,
        "statCurves": {
            "growthCurveHp4Star": 7.275000095367432,
            "growthCurveAtk4Star": 7.275000095367432,
            "growthCurveHp5Star": 7.565999984741211,
            "growthCurveAtk5Star": 7.565999984741211
        }
    },
    {
        "level": 78,
        "statCurves": {
            "growthCurveHp4Star": 7.357999801635742,
            "growthCurveAtk4Star": 7.357999801635742,
            "growthCurveHp5Star": 7.656000137329102,
            "growthCurveAtk5Star": 7.656000137329102
        }
    },
    {
        "level": 79,
        "statCurves": {
            "growthCurveHp4Star": 7.440000057220459,
            "growthCurveAtk4Star": 7.440000057220459,
            "growthCurveHp5Star": 7.745999813079834,
            "growthCurveAtk5Star": 7.745999813079834
        }
    },
    {
        "level": 80,
        "statCurves": {
            "growthCurveHp4Star": 7.5229997634887695,
            "growthCurveAtk4Star": 7.5229997634887695,
            "growthCurveHp5Star": 7.835999965667725,
            "growthCurveAtk5Star": 7.835999965667725
        }
    },
    {
        "level": 81,
        "statCurves": {
            "growthCurveHp4Star": 7.605999946594238,
            "growthCurveAtk4Star": 7.605999946594238,
            "growthCurveHp5Star": 7.926000118255615,
            "growthCurveAtk5Star": 7.926000118255615
        }
    },
    {
        "level": 82,
        "statCurves": {
            "growthCurveHp4Star": 7.688000202178955,
            "growthCurveAtk4Star": 7.688000202178955,
            "growthCurveHp5Star": 8.015999794006348,
            "growthCurveAtk5Star": 8.015999794006348
        }
    },
    {
        "level": 83,
        "statCurves": {
            "growthCurveHp4Star": 7.770999908447266,
            "growthCurveAtk4Star": 7.770999908447266,
            "growthCurveHp5Star": 8.105999946594238,
            "growthCurveAtk5Star": 8.105999946594238
        }
    },
    {
        "level": 84,
        "statCurves": {
            "growthCurveHp4Star": 7.853000164031982,
            "growthCurveAtk4Star": 7.853000164031982,
            "growthCurveHp5Star": 8.196000099182129,
            "growthCurveAtk5Star": 8.196000099182129
        }
    },
    {
        "level": 85,
        "statCurves": {
            "growthCurveHp4Star": 7.935999870300293,
            "growthCurveAtk4Star": 7.935999870300293,
            "growthCurveHp5Star": 8.28600025177002,
            "growthCurveAtk5Star": 8.28600025177002
        }
    },
    {
        "level": 86,
        "statCurves": {
            "growthCurveHp4Star": 8.017999649047852,
            "growthCurveAtk4Star": 8.017999649047852,
            "growthCurveHp5Star": 8.376999855041504,
            "growthCurveAtk5Star": 8.376999855041504
        }
    },
    {
        "level": 87,
        "statCurves": {
            "growthCurveHp4Star": 8.10099983215332,
            "growthCurveAtk4Star": 8.10099983215332,
            "growthCurveHp5Star": 8.467000007629395,
            "growthCurveAtk5Star": 8.467000007629395
        }
    },
    {
        "level": 88,
        "statCurves": {
            "growthCurveHp4Star": 8.182999610900879,
            "growthCurveAtk4Star": 8.182999610900879,
            "growthCurveHp5Star": 8.557999610900879,
            "growthCurveAtk5Star": 8.557999610900879
        }
    },
    {
        "level": 89,
        "statCurves": {
            "growthCurveHp4Star": 8.265999794006348,
            "growthCurveAtk4Star": 8.265999794006348,
            "growthCurveHp5Star": 8.64900016784668,
            "growthCurveAtk5Star": 8.64900016784668
        }
    },
    {
        "level": 90,
        "statCurves": {
            "growthCurveHp4Star": 8.348999977111816,
            "growthCurveAtk4Star": 8.348999977111816,
            "growthCurveHp5Star": 8.73900032043457,
            "growthCurveAtk5Star": 8.73900032043457
        }
    },
    {
        "level": 91,
        "statCurves": {
            "growthCurveHp4Star": 8.430999755859375,
            "growthCurveAtk4Star": 8.430999755859375,
            "growthCurveHp5Star": 8.829999923706055,
            "growthCurveAtk5Star": 8.829999923706055
        }
    },
    {
        "level": 92,
        "statCurves": {
            "growthCurveHp4Star": 8.513999938964844,
            "growthCurveAtk4Star": 8.513999938964844,
            "growthCurveHp5Star": 8.920999526977539,
            "growthCurveAtk5Star": 8.920999526977539
        }
    },
    {
        "level": 93,
        "statCurves": {
            "growthCurveHp4Star": 8.595999717712402,
            "growthCurveAtk4Star": 8.595999717712402,
            "growthCurveHp5Star": 9.01200008392334,
            "growthCurveAtk5Star": 9.01200008392334
        }
    },
    {
        "level": 94,
        "statCurves": {
            "growthCurveHp4Star": 8.678999900817871,
            "growthCurveAtk4Star": 8.678999900817871,
            "growthCurveHp5Star": 9.102999687194824,
            "growthCurveAtk5Star": 9.102999687194824
        }
    },
    {
        "level": 95,
        "statCurves": {
            "growthCurveHp4Star": 8.76099967956543,
            "growthCurveAtk4Star": 8.76099967956543,
            "growthCurveHp5Star": 9.194999694824219,
            "growthCurveAtk5Star": 9.194999694824219
        }
    },
    {
        "level": 96,
        "statCurves": {
            "growthCurveHp4Star": 8.843999862670898,
            "growthCurveAtk4Star": 8.843999862670898,
            "growthCurveHp5Star": 9.28600025177002,
            "growthCurveAtk5Star": 9.28600025177002
        }
    },
    {
        "level": 97,
        "statCurves": {
            "growthCurveHp4Star": 8.927000045776367,
            "growthCurveAtk4Star": 8.927000045776367,
            "growthCurveHp5Star": 9.376999855041504,
            "growthCurveAtk5Star": 9.376999855041504
        }
    },
    {
        "level": 98,
        "statCurves": {
            "growthCurveHp4Star": 9.008999824523926,
            "growthCurveAtk4Star": 9.008999824523926,
            "growthCurveHp5Star": 9.468999862670898,
            "growthCurveAtk5Star": 9.468999862670898
        }
    },
    {
        "level": 99,
        "statCurves": {
            "growthCurveHp4Star": 9.092000007629395,
            "growthCurveAtk4Star": 9.092000007629395,
            "growthCurveHp5Star": 9.5600004196167,
            "growthCurveAtk5Star": 9.5600004196167
        }
    },
    {
        "level": 100,
        "statCurves": {
            "growthCurveHp4Star": 9.173999786376953,
            "growthCurveAtk4Star": 9.173999786376953,
            "growthCurveHp5Star": 9.652000427246094,
            "growthCurveAtk5Star": 9.652000427246094
        }
    }
]